utilities/__init__.py
utilities/_core_errors.py
utilities/altair.py
utilities/asyncio.py
utilities/atools.py
utilities/cachetools.py
utilities/click.py
utilities/concurrent.py
utilities/constants.py
utilities/contextlib.py
utilities/contextvars.py
utilities/core.py
utilities/cvxpy.py
utilities/dataclasses.py
utilities/docker.py
utilities/enum.py
utilities/errors.py
utilities/fastapi.py
utilities/fpdf2.py
utilities/functions.py
utilities/functools.py
utilities/hashlib.py
utilities/http.py
utilities/hypothesis.py
utilities/importlib.py
utilities/inflect.py
utilities/ipython.py
utilities/iterables.py
utilities/jinja2.py
utilities/jupyter.py
utilities/libcst.py
utilities/lightweight_charts.py
utilities/math.py
utilities/memory_profiler.py
utilities/modules.py
utilities/more_itertools.py
utilities/numpy.py
utilities/operator.py
utilities/optuna.py
utilities/orjson.py
utilities/os.py
utilities/packaging.py
utilities/parse.py
utilities/pathlib.py
utilities/platform.py
utilities/polars.py
utilities/polars_ols.py
utilities/postgres.py
utilities/pottery.py
utilities/pqdm.py
utilities/psutil.py
utilities/py.typed
utilities/pydantic.py
utilities/pydantic_settings.py
utilities/pydantic_settings_sops.py
utilities/pyinstrument.py
utilities/pytest.py
utilities/pytest_plugins/__init__.py
utilities/pytest_plugins/pytest_randomly.py
utilities/pytest_plugins/pytest_regressions.py
utilities/pytest_regressions.py
utilities/random.py
utilities/redis.py
utilities/scipy.py
utilities/shellingham.py
utilities/shelve.py
utilities/slack_sdk.py
utilities/sqlalchemy.py
utilities/sqlalchemy_polars.py
utilities/statsmodels.py
utilities/subprocess.py
utilities/testbook.py
utilities/text.py
utilities/threading.py
utilities/throttle.py
utilities/timer.py
utilities/traceback.py
utilities/types.py
utilities/typing.py
utilities/uuid.py
utilities/version.py
utilities/whenever.py
dycw_utilities-0.188.13.dist-info/WHEEL
dycw_utilities-0.188.13.dist-info/entry_points.txt
dycw_utilities-0.188.13.dist-info/METADATA
dycw_utilities-0.188.13.dist-info/RECORD
