Metadata-Version: 2.3
Name: dycw-utilities
Version: 0.188.13
Summary: Miscellaneous Python utilities
Author: Derek Wan
Author-email: Derek Wan <d.wan@icloud.com>
Requires-Dist: coloredlogs>=15.0.1
Requires-Dist: rich>=14.3.1
Requires-Dist: typing-extensions>=4.15.0
Requires-Dist: tzdata>=2025.3
Requires-Dist: tzlocal>=5.3.1
Requires-Dist: whenever>=0.9.5
Requires-Dist: coloredlogs>=15.0.1 ; extra == 'logging'
Requires-Dist: coverage-conditional-plugin>=0.9.0 ; extra == 'test'
Requires-Dist: dycw-pytest-only>=2.1.1 ; extra == 'test'
Requires-Dist: hypothesis>=6.151.4 ; extra == 'test'
Requires-Dist: pytest-asyncio>=1.3.0 ; extra == 'test'
Requires-Dist: pytest-cov>=7.0.0 ; extra == 'test'
Requires-Dist: pytest-instafail>=0.5.0 ; extra == 'test'
Requires-Dist: pytest-lazy-fixtures>=1.4.0 ; extra == 'test'
Requires-Dist: pytest-randomly>=4.0.1 ; extra == 'test'
Requires-Dist: pytest-regressions>=2.9.1 ; extra == 'test'
Requires-Dist: pytest-repeat>=0.9.4 ; extra == 'test'
Requires-Dist: pytest-rerunfailures>=16.1 ; extra == 'test'
Requires-Dist: pytest-rng>=1.0.0 ; extra == 'test'
Requires-Dist: pytest-timeout>=2.4.0 ; extra == 'test'
Requires-Dist: pytest-xdist>=3.8.0 ; extra == 'test'
Requires-Dist: pytest>=9.0.2 ; extra == 'test'
Requires-Python: >=3.12
Provides-Extra: logging
Provides-Extra: test
